package com.google.android.gms.internal;

import java.util.LinkedHashMap;

public class zzhp<K, V>
{
  private int size;
  private final LinkedHashMap<K, V> zzUj;
  private int zzUk;
  private int zzUl;
  private int zzUm;
  private int zzUn;
  private int zzUo;
  private int zzUp;

  public zzhp(int paramInt)
  {
    if (paramInt <= 0)
      throw new IllegalArgumentException("maxSize <= 0");
    this.zzUk = paramInt;
    this.zzUj = new LinkedHashMap(0, 0.75F, true);
  }

  private int zzc(K paramK, V paramV)
  {
    int i = sizeOf(paramK, paramV);
    if (i < 0)
      throw new IllegalStateException("Negative size: " + paramK + "=" + paramV);
    return i;
  }

  protected V create(K paramK)
  {
    return null;
  }

  protected void entryRemoved(boolean paramBoolean, K paramK, V paramV1, V paramV2)
  {
  }

  public final void evictAll()
  {
    trimToSize(-1);
  }

  public final V get(K paramK)
  {
    if (paramK == null)
      throw new NullPointerException("key == null");
    Object localObject3;
    try
    {
      Object localObject2 = this.zzUj.get(paramK);
      if (localObject2 != null)
      {
        this.zzUo = (1 + this.zzUo);
        return localObject2;
      }
      this.zzUp = (1 + this.zzUp);
      localObject3 = create(paramK);
      if (localObject3 == null)
        return null;
    }
    finally
    {
    }
    try
    {
      this.zzUm = (1 + this.zzUm);
      Object localObject5 = this.zzUj.put(paramK, localObject3);
      if (localObject5 != null)
        this.zzUj.put(paramK, localObject5);
      while (true)
      {
        if (localObject5 == null)
          break;
        entryRemoved(false, paramK, localObject3, localObject5);
        return localObject5;
        this.size += zzc(paramK, localObject3);
      }
    }
    finally
    {
    }
    trimToSize(this.zzUk);
    return localObject3;
  }

  public final V put(K paramK, V paramV)
  {
    if ((paramK == null) || (paramV == null))
      throw new NullPointerException("key == null || value == null");
    try
    {
      this.zzUl = (1 + this.zzUl);
      this.size += zzc(paramK, paramV);
      Object localObject2 = this.zzUj.put(paramK, paramV);
      if (localObject2 != null)
        this.size -= zzc(paramK, localObject2);
      if (localObject2 != null)
        entryRemoved(false, paramK, localObject2, paramV);
      trimToSize(this.zzUk);
      return localObject2;
    }
    finally
    {
    }
  }

  public final int size()
  {
    try
    {
      int i = this.size;
      return i;
    }
    finally
    {
      localObject = finally;
      throw localObject;
    }
  }

  protected int sizeOf(K paramK, V paramV)
  {
    return 1;
  }

  public final String toString()
  {
    try
    {
      int i = this.zzUo + this.zzUp;
      int j = 0;
      if (i != 0)
        j = 100 * this.zzUo / i;
      Object[] arrayOfObject = new Object[4];
      arrayOfObject[0] = Integer.valueOf(this.zzUk);
      arrayOfObject[1] = Integer.valueOf(this.zzUo);
      arrayOfObject[2] = Integer.valueOf(this.zzUp);
      arrayOfObject[3] = Integer.valueOf(j);
      String str = String.format("LruCache[maxSize=%d,hits=%d,misses=%d,hitRate=%d%%]", arrayOfObject);
      return str;
    }
    finally
    {
    }
  }

  // ERROR //
  public void trimToSize(int paramInt)
  {
    // Byte code:
    //   0: aload_0
    //   1: monitorenter
    //   2: aload_0
    //   3: getfield 96	com/google/android/gms/internal/zzhp:size	I
    //   6: iflt +20 -> 26
    //   9: aload_0
    //   10: getfield 38	com/google/android/gms/internal/zzhp:zzUj	Ljava/util/LinkedHashMap;
    //   13: invokevirtual 121	java/util/LinkedHashMap:isEmpty	()Z
    //   16: ifeq +48 -> 64
    //   19: aload_0
    //   20: getfield 96	com/google/android/gms/internal/zzhp:size	I
    //   23: ifeq +41 -> 64
    //   26: new 45	java/lang/IllegalStateException
    //   29: dup
    //   30: new 47	java/lang/StringBuilder
    //   33: dup
    //   34: invokespecial 48	java/lang/StringBuilder:<init>	()V
    //   37: aload_0
    //   38: invokevirtual 125	java/lang/Object:getClass	()Ljava/lang/Class;
    //   41: invokevirtual 130	java/lang/Class:getName	()Ljava/lang/String;
    //   44: invokevirtual 54	java/lang/StringBuilder:append	(Ljava/lang/String;)Ljava/lang/StringBuilder;
    //   47: ldc 132
    //   49: invokevirtual 54	java/lang/StringBuilder:append	(Ljava/lang/String;)Ljava/lang/StringBuilder;
    //   52: invokevirtual 63	java/lang/StringBuilder:toString	()Ljava/lang/String;
    //   55: invokespecial 64	java/lang/IllegalStateException:<init>	(Ljava/lang/String;)V
    //   58: athrow
    //   59: astore_2
    //   60: aload_0
    //   61: monitorexit
    //   62: aload_2
    //   63: athrow
    //   64: aload_0
    //   65: getfield 96	com/google/android/gms/internal/zzhp:size	I
    //   68: iload_1
    //   69: if_icmple +13 -> 82
    //   72: aload_0
    //   73: getfield 38	com/google/android/gms/internal/zzhp:zzUj	Ljava/util/LinkedHashMap;
    //   76: invokevirtual 121	java/util/LinkedHashMap:isEmpty	()Z
    //   79: ifeq +6 -> 85
    //   82: aload_0
    //   83: monitorexit
    //   84: return
    //   85: aload_0
    //   86: getfield 38	com/google/android/gms/internal/zzhp:zzUj	Ljava/util/LinkedHashMap;
    //   89: invokevirtual 136	java/util/LinkedHashMap:entrySet	()Ljava/util/Set;
    //   92: invokeinterface 142 1 0
    //   97: invokeinterface 148 1 0
    //   102: checkcast 150	java/util/Map$Entry
    //   105: astore_3
    //   106: aload_3
    //   107: invokeinterface 153 1 0
    //   112: astore 4
    //   114: aload_3
    //   115: invokeinterface 156 1 0
    //   120: astore 5
    //   122: aload_0
    //   123: getfield 38	com/google/android/gms/internal/zzhp:zzUj	Ljava/util/LinkedHashMap;
    //   126: aload 4
    //   128: invokevirtual 159	java/util/LinkedHashMap:remove	(Ljava/lang/Object;)Ljava/lang/Object;
    //   131: pop
    //   132: aload_0
    //   133: aload_0
    //   134: getfield 96	com/google/android/gms/internal/zzhp:size	I
    //   137: aload_0
    //   138: aload 4
    //   140: aload 5
    //   142: invokespecial 98	com/google/android/gms/internal/zzhp:zzc	(Ljava/lang/Object;Ljava/lang/Object;)I
    //   145: isub
    //   146: putfield 96	com/google/android/gms/internal/zzhp:size	I
    //   149: aload_0
    //   150: iconst_1
    //   151: aload_0
    //   152: getfield 161	com/google/android/gms/internal/zzhp:zzUn	I
    //   155: iadd
    //   156: putfield 161	com/google/android/gms/internal/zzhp:zzUn	I
    //   159: aload_0
    //   160: monitorexit
    //   161: aload_0
    //   162: iconst_1
    //   163: aload 4
    //   165: aload 5
    //   167: aconst_null
    //   168: invokevirtual 94	com/google/android/gms/internal/zzhp:entryRemoved	(ZLjava/lang/Object;Ljava/lang/Object;Ljava/lang/Object;)V
    //   171: goto -171 -> 0
    //
    // Exception table:
    //   from	to	target	type
    //   2	26	59	finally
    //   26	59	59	finally
    //   60	62	59	finally
    //   64	82	59	finally
    //   82	84	59	finally
    //   85	161	59	finally
  }
}

/* Location:           /Users/kfinisterre/Desktop/Solo/3DRSoloHacks/unpacked_apk/classes_dex2jar.jar
 * Qualified Name:     com.google.android.gms.internal.zzhp
 * JD-Core Version:    0.6.2
 */